usfiscaldata/__init__.py
usfiscaldata/__main__.py
usfiscaldata/api.py
usfiscaldata/datatypes.py
usfiscaldata/filter_.py
usfiscaldata-0.1.0.dist-info/METADATA
usfiscaldata-0.1.0.dist-info/WHEEL
usfiscaldata-0.1.0.dist-info/licenses/LICENSE
usfiscaldata-0.1.0.dist-info/RECORD
