Metadata-Version: 2.4
Name: usfiscaldata
Version: 0.1.0
Summary: Client for US Treasury Fiscal Data API
Project-URL: Homepage, https://github.com/christopherdoyle/usfiscaldata
Project-URL: Issues, https://github.com/christopherdoyle/usfiscaldata/issues
Author: Christopher Doyle
License-Expression: MIT
License-File: LICENSE
Requires-Python: >=3.8
Requires-Dist: requests<3,>=2.0
